LICENSE
README.md
setup.py
up_ac/AC_interface.py
up_ac/Irace_configurator.py
up_ac/Irace_interface.py
up_ac/OAT_configurator.py
up_ac/OAT_interface.py
up_ac/Selector_configurator.py
up_ac/Selector_interface.py
up_ac/Smac_configurator.py
up_ac/Smac_interface.py
up_ac/__init__.py
up_ac/configurators.py
up_ac.egg-info/PKG-INFO
up_ac.egg-info/SOURCES.txt
up_ac.egg-info/dependency_links.txt
up_ac.egg-info/requires.txt
up_ac.egg-info/top_level.txt
up_ac/engine_pcs/enhsp-any.pcs
up_ac/engine_pcs/enhsp.pcs
up_ac/engine_pcs/fast-downward.pcs
up_ac/engine_pcs/fmap.pcs
up_ac/engine_pcs/lpg-anytime.pcs
up_ac/engine_pcs/lpg.pcs
up_ac/engine_pcs/lpg_to_revise.pcs
up_ac/engine_pcs/pyperplan.pcs
up_ac/engine_pcs/symk.pcs
up_ac/engine_pcs/tamer.pcs
up_ac/test_problems/citycar/domain.pddl
up_ac/test_problems/citycar/problem.pddl
up_ac/test_problems/counters/domain.pddl
up_ac/test_problems/counters/problem.pddl
up_ac/test_problems/counters/problem2.pddl
up_ac/test_problems/depot/domain.pddl
up_ac/test_problems/depot/problem.pddl
up_ac/test_problems/htn-transport/domain.hddl
up_ac/test_problems/htn-transport/problem.hddl
up_ac/test_problems/matchcellar/domain.pddl
up_ac/test_problems/matchcellar/problem.pddl
up_ac/test_problems/miconic/domain.pddl
up_ac/test_problems/miconic/problem.pddl
up_ac/test_problems/robot_fastener/domain.pddl
up_ac/test_problems/robot_fastener/problem.pddl
up_ac/test_problems/safe_road/domain.pddl
up_ac/test_problems/safe_road/problem.pddl
up_ac/test_problems/sailing/domain.pddl
up_ac/test_problems/sailing/problem.pddl
up_ac/test_problems/visit_precedence/domain.pddl
up_ac/test_problems/visit_precedence/problem.pddl
up_ac/utils/__init__.py
up_ac/utils/ac_feedback.py
up_ac/utils/call_engine_OAT.py
up_ac/utils/download_OAT.py
up_ac/utils/load_smac_feedback.py
up_ac/utils/parametrizable_engines.py
up_ac/utils/patch_daskrunner.py
up_ac/utils/patches.py
up_ac/utils/pcs_transform.py
up_ac/utils/sel_call_up.py
up_ac/utils/timeout.py
up_ac/utils/timer.py
up_ac/utils/up_ac_wrapper.py