Metadata-Version: 2.1
Name: up_ac
Version: 0.0.1.1
Summary: An Algorithm Configuration package for unified-planning.
Home-page: https://github.com/DimitriWeiss/up-ac.git
Author: Dimitri Weiß
Author-email: dimitri-weiss@web.com
License: LICENSE.txt
License-File: LICENSE
Requires-Dist: unified-planning
Requires-Dist: ConfigSpace
Requires-Dist: tarski
Requires-Dist: pebble
Requires-Dist: dill
